kaggle_colab/__init__.py
kaggle_colab/core.py
kaggle_colab-0.1.1.dist-info/LICENSE
kaggle_colab-0.1.1.dist-info/METADATA
kaggle_colab-0.1.1.dist-info/WHEEL
kaggle_colab-0.1.1.dist-info/top_level.txt
kaggle_colab-0.1.1.dist-info/RECORD
