Metadata-Version: 2.1
Name: kaggle-colab
Version: 0.1.1
Summary: Minimalistic tool for easily setting up and switching between Kaggle and Google Colab environments from a GitHub repository, to leverage their GPU-accelerated hardware
Home-page: https://github.com/pgmesa/kaggle-colab
Author: Pablo García Mesa
Author-email: pgmesa.sm@gmail.com
Classifier: Programming Language :: Python :: 3.9
Classifier: License :: OSI Approved :: MIT License
Classifier: Operating System :: OS Independent
Requires-Python: >=3.9
License-File: LICENSE
